[
  {
    "orderId": 0,
    "imageUrl": "/images/paorderId/force1.png",
    "name": "Nike x Supreme Air Force 1 Low Flax",
    "category": "남여 공용",
    "color": "Brown",
    "size": "275",
    "quantity": 1,
    "purchasePrice": "335000"
  },
  {
    "orderId": 1,
    "imageUrl": "/images/paorderId/travis.webp",
    "name": "Jordan 1 x Travis Scott Retro OG",
    "category": "여성 신발",
    "color": "White / Green",
    "size": "250",
    "quantity": 3,
    "purchasePrice": "450000"
  },
  {
    "orderId": 2,
    "imageUrl": "/images/paorderId/lee.png",
    "name": "Nike Paris Saint-Germain 2023/24 Dri-Fit Stadium",
    "category": "남여 공용",
    "color": "White / Blue",
    "size": "FREE",
    "quantity": 1,
    "purchasePrice": "280000"
  },
  {
    "orderId": 3,
    "imageUrl": "/images/paorderId/force.png",
    "name": "Nike Air Force 1 '07 LV8 MorderIdnight Navy",
    "category": "남성 신발",
    "color": "Navy",
    "size": "285",
    "quantity": 1,
    "purchasePrice": "200000"
  },
  {
    "orderId": 4,
    "imageUrl": "/images/paorderId/martin.webp",
    "name": "Nike x Martine Rose Shox MR4 Safety Orange",
    "category": "여성 신발",
    "color": "White / Yellow",
    "size": "255",
    "quantity": 2,
    "purchasePrice": "382000"
  }
]
